sprawl/__init__.py
sprawl/loud_log.py
sprawl-0.1.2.dist-info/WHEEL
sprawl-0.1.2.dist-info/METADATA
sprawl-0.1.2.dist-info/RECORD
