Metadata-Version: 2.1
Name: sprawl
Version: 0.1.2
Summary: 
Author: Levi Notik
Author-email: projects@levinotik.com
Requires-Python: >=3.7,<4.0
Classifier: Programming Language :: Python :: 3
Classifier: Programming Language :: Python :: 3.7
Requires-Dist: termcolor (>=1.1.0,<2.0.0)
